tests/__init__.py
tests/advanced_analysis_test.py
tests/manipulation_test.py
tests/statistics_test.py
tests/visualization_test.py
datalib_kh-0.1.0.dist-info/LICENSE
datalib_kh-0.1.0.dist-info/METADATA
datalib_kh-0.1.0.dist-info/WHEEL
datalib_kh-0.1.0.dist-info/top_level.txt
datalib_kh-0.1.0.dist-info/RECORD
